act4e_mcdp/__init__.py
act4e_mcdp/autogen_packed_test_data.py
act4e_mcdp/coords.py
act4e_mcdp/download.py
act4e_mcdp/loading.py
act4e_mcdp/main_solve_dp.py
act4e_mcdp/main_solve_dp_queries.py
act4e_mcdp/main_solve_mcdp.py
act4e_mcdp/mcdp_solution_interface.py
act4e_mcdp/nameddps.py
act4e_mcdp/posets.py
act4e_mcdp/primitivedps.py
act4e_mcdp/py.typed
act4e_mcdp/solution_interface.py
act4e_mcdp/utils.py
act4e_mcdp-0.8.2.dist-info/METADATA
act4e_mcdp-0.8.2.dist-info/WHEEL
act4e_mcdp-0.8.2.dist-info/entry_points.txt
act4e_mcdp-0.8.2.dist-info/RECORD
